mongodb_connect/__init__.py
mongodb_connect/mongo_crud.py
load_MongoDB-0.0.1.dist-info/METADATA
load_MongoDB-0.0.1.dist-info/WHEEL
load_MongoDB-0.0.1.dist-info/top_level.txt
load_MongoDB-0.0.1.dist-info/RECORD
